README.md
setup.py
firstblood/__init__.py
firstblood/all.py
firstblood.egg-info/PKG-INFO
firstblood.egg-info/SOURCES.txt
firstblood.egg-info/dependency_links.txt
firstblood.egg-info/top_level.txt
firstblood/modulo/__init__.py
firstblood/patches/__init__.py
firstblood/patches/abc.py
firstblood/patches/bytes.py
firstblood/patches/conv.py
firstblood/patches/float.py
firstblood/patches/function.py
firstblood/patches/hash.py
firstblood/patches/int.py
firstblood/patches/iterable.py
firstblood/patches/json.py
firstblood/patches/len.py
firstblood/patches/object.py
firstblood/patches/patch.py
firstblood/patches/str.py
firstblood/unifiedIO/__init__.py
firstblood/unifiedIO/shortcuts.py
firstblood/unifiedIO/unified.py