Metadata-Version: 2.1
Name: firstblood
Version: 0.0.1
Summary: Write exploit faster with up-to-date python 3
Home-page: https://github.com/sasdf/firstblood
Author: sasdf
Author-email: 
License: UNKNOWN
Platform: UNKNOWN
Classifier: Programming Language :: Python :: 3 :: Only
Classifier: Development Status :: 1 - Planning
Classifier: Environment :: Plugins
Classifier: Intended Audience :: Developers
Classifier: License :: Other/Proprietary License
Classifier: Operating System :: OS Independent
Classifier: Topic :: Security
Classifier: Topic :: Software Development :: Libraries
